requtests/__init__.py
requtests/fake_adapter.py
requtests/fake_request.py
requtests/fake_response.py
requtests/parsed_request.py
requtests/protocols.py
requtests-1.2.0.dist-info/LICENSE
requtests-1.2.0.dist-info/METADATA
requtests-1.2.0.dist-info/WHEEL
requtests-1.2.0.dist-info/top_level.txt
requtests-1.2.0.dist-info/RECORD
