Metadata-Version: 2.1
Name: requtests
Version: 1.2.0
Summary: Test helpers for the requests library.
Home-page: https://github.com/funnel-io/requtests
Author: The Funnel Dev Team
Author-email: open-source@funnel.io
License: MIT
Project-URL: Bug Reports, https://github.com/funnel-io/requtests/issues
Project-URL: Source, https://github.com/funnel-io/requtests
Keywords: ["Requests Testing"]
Classifier: Development Status :: 5 - Production/Stable
Classifier: License :: OSI Approved :: MIT License
Classifier: Programming Language :: Python :: 3
Classifier: Programming Language :: Python :: 3.8
Classifier: Programming Language :: Python :: 3.9
Classifier: Programming Language :: Python :: 3.10
Classifier: Programming Language :: Python :: 3.11
Classifier: Programming Language :: Python :: 3.12
Classifier: Topic :: Software Development :: Libraries
License-File: LICENSE
Requires-Dist: requests
